Workbook

Sheet 15-Sep
B2: FOURTEEN GROUP OF COMPANIES · AWAMI MARKET, KARKHANO, PESHAWAR | G2: Closing date | H2: 46280
B3: Closing — Rashid's Software, CRM & Salary | G3: Entries | H3: 7 JVs · 14 lines
B5: Period | D5: From – to | E5: Software & CRM | F5: Salary | G5: Total paid | H5: Owed to FMH + KBH
B6: 43 days | D6: 24-Apr-26 → 05-Jun-26 | E6: =H27 | F6: =H28 | G6: =H22 | H6: =-(H10+H11)
B8: Balances brought forward and closing | H8: Amounts in brackets are what Awami owes
B9: Code | C9: Account | E9: Opening b/f | F9: Debit | G9: Credit | H9: Closing
B10: 22100 | C10: FMH - Fourteen Manzil Heights | E10: 0 | F10: =SUMIFS(Entries!$G$2:$G$155,Entries!$C$2:$C$155,"Due to / from Group Companies:FMH - Fourteen Manzil Heights",Entries!$J$2:$J$155,"15-Sep") | G10: =SUMIFS(Entries!$H$2:$H$155,Entries!$C$2:$C$155,"Due to / from Group Companies:FMH - Fourteen Manzil Heights",Entries!$J$2:$J$155,"15-Sep") | H10: =E10+F10-G10
B11: 22200 | C11: KBH - Khushal Bagh Heights | E11: 0 | F11: =SUMIFS(Entries!$G$2:$G$155,Entries!$C$2:$C$155,"Due to / from Group Companies:KBH - Khushal Bagh Heights",Entries!$J$2:$J$155,"15-Sep") | G11: =SUMIFS(Entries!$H$2:$H$155,Entries!$C$2:$C$155,"Due to / from Group Companies:KBH - Khushal Bagh Heights",Entries!$J$2:$J$155,"15-Sep") | H11: =E11+F11-G11
B13: Payments made on Awami's behalf | H13: Paid by FMH or KBH · no Awami cash or bank used
B14: Date | C14: Voucher | D14: Description | E14: Head (COA) | F14: Payee | G14: Paid through | H14: Amount
B15: 46136 | C15: JV-0025 | D15: Paid for laptop c/o Rashid | E15: 15300 · Computer & IT Equipment | F15: Rashid | G15: FMH | H15: 95000
B16: 46147 | C16: JV-0029 | D16: Paid to Rashid as salary April 2026 | E16: 70100 · Salaries & Wages | F16: Rashid | G16: FMH | H16: 50000
B17: 46164 | C17: JV-0052 | D17: Paid to Rashid Mansoor for CRM software - KBH ref CPV-8199 | E17: 16100 · Software & Licences | F17: Rashid | G17: KBH | H17: 8000
B18: 46165 | C18: JV-0053 | D18: Paid to Rashid Mansoor for QuickBooks - KBH ref CPV-8219 | E18: 16100 · Software & Licences | F18: Rashid | G18: KBH | H18: 100000
B19: 46167 | C19: JV-0054 | D19: Paid to Rashid Mansoor for QuickBooks - KBH ref CPV-8222 | E19: 16100 · Software & Licences | F19: Rashid | G19: KBH | H19: 200000
B20: 46175 | C20: JV-0032 | D20: Paid to Rashid saib for QuickBooks software | E20: 16100 · Software & Licences | F20: Rashid | G20: FMH | H20: 80000
B21: 46178 | C21: JV-0030 | D21: Paid to Rashid for QuickBooks | E21: 16100 · Software & Licences | F21: Rashid | G21: FMH | H21: 100000
B22: ="FMH "&TEXT(SUMIFS(H15:H21,G15:G21,"FMH"),"#,##0")&" · KBH "&TEXT(SUMIFS(H15:H21,G15:G21,"KBH"),"#,##0") | G22: Total paid | H22: =SUM(H15:H21)
B24: Summary by head | H24: Expenses and assets charged
B25: Code | C25: Head | H25: Amount
B26: 15300 | C26: Computer & IT Equipment | H26: =SUMIFS(Entries!$G$2:$G$155,Entries!$C$2:$C$155,"Fixed Assets:Computer & IT Equipment",Entries!$J$2:$J$155,"15-Sep")-SUMIFS(Entries!$H$2:$H$155,Entries!$C$2:$C$155,"Fixed Assets:Computer & IT Equipment",Entries!$J$2:$J$155,"15-Sep")
B27: 16100 | C27: Software & Licences | H27: =SUMIFS(Entries!$G$2:$G$155,Entries!$C$2:$C$155,"Other Assets:Software & Licences",Entries!$J$2:$J$155,"15-Sep")-SUMIFS(Entries!$H$2:$H$155,Entries!$C$2:$C$155,"Other Assets:Software & Licences",Entries!$J$2:$J$155,"15-Sep")
B28: 70100 | C28: Salaries & Wages | H28: =SUMIFS(Entries!$G$2:$G$155,Entries!$C$2:$C$155,"Administrative Expenses:Salaries & Wages",Entries!$J$2:$J$155,"15-Sep")-SUMIFS(Entries!$H$2:$H$155,Entries!$C$2:$C$155,"Administrative Expenses:Salaries & Wages",Entries!$J$2:$J$155,"15-Sep")
G29: Total | H29: =SUM(H26:H28)
B31: Checks
C32: 1 | D32: Payments total ties to balances owed | G32: Must pass | H32: =IF(K32=0,"✓ OK","✗ "&K32&" issue") | K32: =IF(ROUND(H22-H6,0)=0,0,1)
C33: 2 | D33: Payments + head summary tie | G33: Must pass | H33: =IF(K33=0,"✓ OK","✗ "&K33&" issue") | K33: =IF(ROUND(H22-H29,0)=0,0,1)
B35: Remarks
B36: These are Rashid's own software (QuickBooks/CRM) and salary payments, funded by FMH/KBH on Awami's behalf — carved out of the 16-Sep closing at his request, purely for how it's presented here. QuickBooks itself needs no change: these entries are already posted there correctly under the FMH/KBH journal entries.
B40: Prepared by (Accountant) | D40: Checked by | G40: Approved by (Director)
B42: Source: Awami_All_Entries.xlsx (Entries sheet) · Split out from 16-Sep at Rashid's instruction · Dates are voucher dates

Sheet 16-Sep
B2: FOURTEEN GROUP OF COMPANIES · AWAMI MARKET, KARKHANO, PESHAWAR | G2: Closing date | H2: 46281
B3: Consolidated Closing — All Entries to Date | G3: Entries | H3: 57 JVs · 140 lines
B5: Period | D5: From – to | E5: Token money (net) | F5: Expenses paid | G5: With Yousaf Shah | H5: Owed to FMH + KBH
B6: 225 days | D6: 06-Feb-26 → 18-Sep-26 | E6: =H37 | F6: =H75 | G6: =H14 | H6: =-(H15+H16)
B8: Balances brought forward and closing | H8: Amounts in brackets are what Awami owes
B9: Code | C9: Account | E9: Opening b/f | F9: Debit | G9: Credit | H9: Closing
B10: 10100 | C10: Cash in Hand | E10: 0 | F10: =SUMIFS(Entries!$G$2:$G$155,Entries!$C$2:$C$155,"Cash & Bank:Cash in Hand") | G10: =SUMIFS(Entries!$H$2:$H$155,Entries!$C$2:$C$155,"Cash & Bank:Cash in Hand") | H10: =E10+F10-G10
B11: 10200 | C11: Petty Cash | E11: 0 | F11: =SUMIFS(Entries!$G$2:$G$155,Entries!$C$2:$C$155,"Cash & Bank:Petty Cash") | G11: =SUMIFS(Entries!$H$2:$H$155,Entries!$C$2:$C$155,"Cash & Bank:Petty Cash") | H11: =E11+F11-G11
B12: 10300 | C12: Bank Al-Habib - Awami Market | E12: 0 | F12: =SUMIFS(Entries!$G$2:$G$155,Entries!$C$2:$C$155,"Cash & Bank:Bank Al-Habib - Awami Market") | G12: =SUMIFS(Entries!$H$2:$H$155,Entries!$C$2:$C$155,"Cash & Bank:Bank Al-Habib - Awami Market") | H12: =E12+F12-G12
B13: Not cash — money held or owed on Awami's behalf
B14: 12610 | C14: Due from Syed Yousaf Shah (receivable, not cash) | E14: 0 | F14: =SUMIFS(Entries!$G$2:$G$158,Entries!$C$2:$C$158,"Current Assets:Due from Directors:Syed Yousaf Shah") | G14: =SUMIFS(Entries!$H$2:$H$158,Entries!$C$2:$C$158,"Current Assets:Due from Directors:Syed Yousaf Shah") | H14: =E14+F14-G14
B15: 22100 | C15: FMH - Fourteen Manzil Heights | E15: 0 | F15: =SUMIFS(Entries!$G$2:$G$155,Entries!$C$2:$C$155,"Due to / from Group Companies:FMH - Fourteen Manzil Heights",Entries!$J$2:$J$155,"16-Sep") | G15: =SUMIFS(Entries!$H$2:$H$155,Entries!$C$2:$C$155,"Due to / from Group Companies:FMH - Fourteen Manzil Heights",Entries!$J$2:$J$155,"16-Sep") | H15: =E15+F15-G15
B16: 22200 | C16: KBH - Khushal Bagh Heights | E16: 0 | F16: =SUMIFS(Entries!$G$2:$G$155,Entries!$C$2:$C$155,"Due to / from Group Companies:KBH - Khushal Bagh Heights",Entries!$J$2:$J$155,"16-Sep") | G16: =SUMIFS(Entries!$H$2:$H$155,Entries!$C$2:$C$155,"Due to / from Group Companies:KBH - Khushal Bagh Heights",Entries!$J$2:$J$155,"16-Sep") | H16: =E16+F16-G16
B17: 21100 | C17: Token Money - Units (customer advances) | E17: 0 | F17: =SUMIFS(Entries!$G$2:$G$155,Entries!$C$2:$C$155,"Customer Advances:Token Money - Units") | G17: =SUMIFS(Entries!$H$2:$H$155,Entries!$C$2:$C$155,"Customer Advances:Token Money - Units") | H17: =E17+F17-G17
B19: Token money received | H19: Credit 21100 · money came in through FMH office or director
B20: Date | C20: Voucher | D20: Token · buyer : units | F20: Class | G20: Received through | H20: Amount
B21: 46189 | C21: JV-0016 | D21: Token 101 · Abdullah: LG-03 | F21: LG | G21: FMH | H21: 250000
B22: 46213 | C22: JV-0001 | D22: Token 102 · Suhail: GF-129 | F22: GF | G22: FMH · Cash | H22: 10000
B23: 46232 | C23: JV-0002 | D23: Token 103 · Hassan Jan: GF-129 | F23: GF | G23: FMH · Online to 14 Development | H23: 40000
B24: 46253 | C24: JV-0003 | D24: Token 105 · Raza Ullah: GF-112 | F24: GF | G24: FMH · Cash | H24: 10000
B25: 46253 | C25: JV-0004 | D25: Token 106 · Raza Ullah: GF-176 | F25: GF | G25: FMH · Cash | H25: 10000
B26: 46262 | C26: JV-0005 | D26: Token 107 · Samin Khan Bangash: LG-132, LG-133 | F26: LG | G26: FMH · Cash | H26: 10000
B27: 46266 | C27: JV-0006 | D27: Token 108 · Hassan Jan: GF-129 | F27: GF | G27: FMH · Online to 14 Development | H27: 100000
B28: 46269 | C28: JV-0007 | D28: Token 109 · Haji Ibrar: LG-05, LG-06 · Waqar Ahmad - Units: LG-47 to LG-50, LG-91 to LG-93 | F28: LG | G28: FMH · Cash | H28: 500000
B29: 46269 | C29: JV-0008 | D29: Token 110 · Hussain: LG-54, LG-97 | F29: LG | G29: FMH · Cash | H29: 200000
B30: 46270 | C30: JV-0009 | D30: Token 111 · Haji Ibrar: LG-01 to LG-09 | F30: LG | G30: FMH · Cash | H30: 600000
B31: 46270 | C31: JV-0010 | D31: Token 112 · Malak Ibrar: GF-13 | F31: GF | G31: FMH · Cash | H31: 500000
B32: 46276 | C32: JV-0011 | D32: Token 113 · Meena Gul: LG-51 to LG-53, LG-94 to LG-96, GF-90 | F32: GF/LG | G32: Syed Yousaf Shah · Cash | H32: 800000
... B36: 46283 | C36: JV-0017 | D36: Refund: Token 101 · Abdullah: LG-03 | F36: LG | G36: FMH | H36: -250000
B37: 15 tokens received, 1 refunded | G37: Net token money | H37: =SUM(H21:H36)
B39: Payments made on Awami's behalf | H39: Paid by FMH, KBH or director · no Awami cash or bank used
B40: Date | C40: Voucher | D40: Description | E40: Head (COA) | F40: Payee | G40: Paid through | H40: Amount
B41: 46059 | C41: JV-0018 | D41: Ch# 10318764 deposited to Yousaf saib UBL | E41: 51100 · Land Purchase Cost | F41: Syed Yousaf Shah | G41: FMH | H41: 10000000
B42: 46111 | C42: JV-0019 | D42: Ch# 10323992 issued to Yousaf saib as loan return | E42: 51100 · Land Purchase Cost | F42: Syed Yousaf Shah | G42: FMH | H42: 4000000
B43: 46111 | C43: JV-0020 | D43: Ch# 10323992 issued to Yousaf saib as loan return - second entry | E43: 51100 · Land Purchase Cost | F43: Syed Yousaf Shah | G43: FMH | H43: 4000000
B44: 46129 | C44: JV-0021 | D44: Paid to Kashif as stamp navi | E44: 70500 · Printing & Stationery | F44: Kashif | G44: FMH | H44: 15000
B45: 46132 | C45: JV-0022 | D45: Paid to Waqar easypaisa for project MAP | E45: 60300 · Marketing Printing & Material | F45: Waqar Easypaisa | G45: FMH | H45: 10000
B46: 46133 | C46: JV-0023 | D46: Paid to Shah Khalid online by Naeem saib | E46: 53100 · Architecture, Design & Drawings | F46: Shah Khalid | G46: FMH | H46: 500000
B47: 46135 | C47: JV-0024 | D47: Ch# 10324016 issued to Alam c/o Dr Irshad | E47: 53200 · Soil Testing & Survey | F47: Alam | G47: FMH | H47: 100000
B48: 46139 | C48: JV-0026 | D48: Paid for Kharkhano map laptop | E48: 15300 · Computer & IT Equipment | G48: FMH | H48: 35000
B49: 46142 | C49: JV-0027 | D49: Paid to Noor Zaman TMA b/o Yousaf saib | E49: 53500 · Regulatory & Facilitation | F49: Noor Zaman TMA | G49: FMH | H49: 100000
B50: 46146 | C50: JV-0028 | D50: Paid to Alam c/o Dr Irshad | E50: 53200 · Soil Testing & Survey | F50: Alam | G50: FMH | H50: 100000
B51: 46163 | C51: JV-0031 | D51: Paid to RX Printings, receipts etc | E51: 70500 · Printing & Stationery | F51: RX Printings | G51: FMH | H51: 20000
B52: 46168 | C52: JV-0055 | D52: Paid to Patwari for Karkhano project by Syed Yousaf Shah - KBH ref CPV-8264 | E52: 53500 · Regulatory & Facilitation | F52: Patwari | G52: KBH | H52: 100000
B53: 46178 | C53: JV-0033 | D53: Paid for receipt books CRV CPV and tokens, Awami mobile | E53: 70500 · Printing & Stationery | G53: FMH | H53: 45000
B54: 46181 | C54: JV-0034 | D54: Ch# 10324046 issued to PRF | E54: 53400 · Government & Regulatory Fees | F54: PRF | G54: FMH | H54: 850000
B55: 46181 | C55: JV-0057 | D55: Paid to Jawad - two colour print map of Karkhano - KBH ref CPV-8328 | E55: 60300 · Marketing Printing & Material | F55: Jawad | G55: KBH | H55: 3000
B56: 46182 | C56: JV-0035 | D56: Ch# 10324047 issued for soil testing by Eng Hamza | E56: 53200 · Soil Testing & Survey | F56: Eng Hamza | G56: FMH | H56: 100000
B57: 46182 | C57: JV-0036 | D57: Ch# 10324048 issued for KPRA payment by Yousaf saib | E57: 53400 · Government & Regulatory Fees | F57: KPRA | G57: FMH | H57: 350000
B58: 46184 | C58: JV-0037 | D58: Ch# 10324043 issued to PDA | E58: 53500 · Regulatory & Facilitation | F58: PDA | G58: FMH | H58: 375000
B59: 46184 | C59: JV-0038 | D59: Paid to Yousaf saib as NOC payment PDA | E59: 53300 · NOC & Approvals | F59: Syed Yousaf Shah | G59: FMH | H59: 50000
B60: 46184 | C60: JV-0039 | D60: Paid to Fayyaz for A3 map printing | E60: 60300 · Marketing Printing & Material | F60: Fayyaz Printing | G60: FMH | H60: 1500
B61: 46184 | C61: JV-0040 | D61: Paid to RX Printings for Awami Market printing | E61: 60300 · Marketing Printing & Material | F61: RX Printings | G61: FMH | H61: 28000
B62: 46185 | C62: JV-0041 | D62: Paid for Kharkhano map A6 size printing | E62: 60300 · Marketing Printing & Material | G62: FMH | H62: 5200
B63: 46190 | C63: JV-0042 | D63: Paid to Momain photocopy online | E63: 70500 · Printing & Stationery | F63: Momain Photocopy | G63: FMH | H63: 18250
B64: 46196 | C64: JV-0058 | D64: Paid to Jawad - printing map of Awami Market - KBH ref CPV-8444 | E64: 60300 · Marketing Printing & Material | F64: Jawad | G64: KBH | H64: 3000
B65: 46203 | C65: JV-0059 | D65: Paid to Jawad - colour print map A1, eight copies - KBH ref CPV-8497 | E65: 60300 · Marketing Printing & Material | F65: Jawad | G65: KBH | H65: 15500
B66: 46206 | C66: JV-0060 | D66: Paid online to Asif Akhtar for 3D animation, through Jawad - KBH ref CPV-8526 | E66: 60100 · Advertising & Promotion | F66: Asif Akhtar | G66: KBH | H66: 50000
B67: 46218 | C67: JV-0061 | D67: Paid online to Asif Akhtar for 3D animation, through Jawad - KBH ref CPV-8624 | E67: 60100 · Advertising & Promotion | F67: Asif Akhtar | G67: KBH | H67: 50000
B68: 46224 | C68: JV-0043 | D68: Paid to Sabir for structure design | E68: 53100 · Architecture, Design & Drawings | F68: Sabir | G68: FMH | H68: 500000
B69: 46242 | C69: JV-0062 | D69: Paid online to Asif Akhtar for 3D animation by Syed Yousaf Shah, deducted from his loan - KBH ref JV-924 | E69: 60100 · Advertising & Promotion | F69: Asif Akhtar | G69: KBH | H69: 100000
B70: 46258 | C70: JV-0064 | D70: Speed money to Waqar Ahmed for Karkhano, deducted from Syed Yousaf Shah loan - KBH ref JV-942 | E70: 53500 · Regulatory & Facilitation | F70: Waqar Ahmad | G70: KBH | H70: 20000
B71: 46272 | C71: JV-0045 | D71: Dinner with clients by Syed Yousaf Shah | E71: 60400 · Events & Client Entertainment | G71: Syed Yousaf Shah | H71: 43600
B72: 46275 | C72: JV-0046 | D72: Karkhano map printing | E72: 60300 · Marketing Printing & Material | G72: Syed Yousaf Shah | H72: 16000
B73: 46276 | C73: JV-0047 | D73: Khatam ul Quran | E73: 81100 · Donations, Sadqa & Khairat | G73: Syed Yousaf Shah | H73: 27000
B74: 46278 | C74: JV-0050 | D74: Khairat at Karkhano | E74: 81100 · Donations, Sadqa & Khairat | G74: Syed Yousaf Shah | H74: 29000
B75: ="FMH "&TEXT(SUMIFS(H41:H81,G41:G81,"FMH"),"#,##0")&" · KBH "&TEXT(SUMIFS(H41:H81,G41:G81,"KBH"),"#,##0")&" · Yousaf Shah "&TEXT(SUMIFS(H41:H81,G41:G81,"Syed Yousaf Shah"),"#,##0") | G75: ="FMH "&TEXT(SUMIFS(H41:H74,G41:G74,"FMH"),"#,##0")&" · KBH "&TEXT(SUMIFS(H41:H74,G41:G74,"KBH"),"#,##0")&" · Yousaf Shah "&TEXT(SUMIFS(H41:H74,G41:G74,"Syed Yousaf Shah"),"#,##0") | H75: =SUM(H41:H74)
B77: Money moved between parties | H77: Handed over or lent · no income or expense
B78: Date | C78: Voucher | D78: Description | E78: From | F78: To | H78: Amount
B79: 46181 | C79: JV-0056 | D79: Cash handed over to Syed Yousaf Shah through Jawad - KBH ref CPV-8327 | E79: KBH | F79: Syed Yousaf Shah | H79: 1000000
B80: 46253 | C80: JV-0063 | D80: Cash of unit UG-06, Arbab Zubair Khan, CRV-10013, taken by Syed Yousaf Shah - KBH ref JV-939 | E80: KBH | F80: Syed Yousaf Shah | H80: 4900000
B81: 46272 | C81: JV-0044 | D81: Paid to Ismail and Mikael, FMH landlord, as loan to FMH | E81: Syed Yousaf Shah | F81: FMH | H81: 1000000
B82: 46276 | C82: JV-0015 | D82: Token money handed over by FMH office | E82: FMH | F82: Syed Yousaf Shah | H82: 2300000
B83: 46277 | C83: JV-0048 | D83: Paid for FMH head office construction | E83: Syed Yousaf Shah | F83: FMH | H83: 76500
B84: 46277 | C84: JV-0049 | D84: Paid for FMH head office construction | E84: Syed Yousaf Shah | F84: FMH | H84: 73000
B85: 46278 | C85: JV-0051 | D85: Paid for FMH head office construction, bricks | E85: Syed Yousaf Shah | F85: FMH | H85: 74000
G86: Total moved | H86: =SUM(H79:H85)
B88: Summary by head | H88: Expenses and assets charged
B89: Code | C89: Head | H89: Amount
B90: 15300 | C90: Computer & IT Equipment | F90: Fixed Assets | H90: =SUMIFS(Entries!$G$2:$G$155,Entries!$C$2:$C$155,"Fixed Assets:Computer & IT Equipment",Entries!$J$2:$J$155,"16-Sep")-SUMIFS(Entries!$H$2:$H$155,Entries!$C$2:$C$155,"Fixed Assets:Computer & IT Equipment",Entries!$J$2:$J$155,"16-Sep")
B91: 16100 | C91: Software & Licences | F91: Other Assets | H91: =SUMIFS(Entries!$G$2:$G$155,Entries!$C$2:$C$155,"Other Assets:Software & Licences",Entries!$J$2:$J$155,"16-Sep")-SUMIFS(Entries!$H$2:$H$155,Entries!$C$2:$C$155,"Other Assets:Software & Licences",Entries!$J$2:$J$155,"16-Sep")
B92: 51100 | C92: Land Purchase Cost | F92: Cost of Sales | H92: =SUMIFS(Entries!$G$2:$G$155,Entries!$C$2:$C$155,"Cost of Sales:Land Cost:Land Purchase Cost")-SUMIFS(Entries!$H$2:$H$155,Entries!$C$2:$C$155,"Cost of Sales:Land Cost:Land Purchase Cost")
B93: 53100 | C93: Architecture, Design & Drawings | F93: Cost of Sales | H93: =SUMIFS(Entries!$G$2:$G$155,Entries!$C$2:$C$155,"Cost of Sales:Project Development Cost:Architecture, Design & Drawings")-SUMIFS(Entries!$H$2:$H$155,Entries!$C$2:$C$155,"Cost of Sales:Project Development Cost:Architecture, Design & Drawings")
B94: 53200 | C94: Soil Testing & Survey | F94: Cost of Sales | H94: =SUMIFS(Entries!$G$2:$G$155,Entries!$C$2:$C$155,"Cost of Sales:Project Development Cost:Soil Testing & Survey")-SUMIFS(Entries!$H$2:$H$155,Entries!$C$2:$C$155,"Cost of Sales:Project Development Cost:Soil Testing & Survey")
B95: 53300 | C95: NOC & Approvals | F95: Cost of Sales | H95: =SUMIFS(Entries!$G$2:$G$155,Entries!$C$2:$C$155,"Cost of Sales:Project Development Cost:NOC & Approvals")-SUMIFS(Entries!$H$2:$H$155,Entries!$C$2:$C$155,"Cost of Sales:Project Development Cost:NOC & Approvals")
B96: 53400 | C96: Government & Regulatory Fees | F96: Cost of Sales | H96: =SUMIFS(Entries!$G$2:$G$155,Entries!$C$2:$C$155,"Cost of Sales:Project Development Cost:Government & Regulatory Fees")-SUMIFS(Entries!$H$2:$H$155,Entries!$C$2:$C$155,"Cost of Sales:Project Development Cost:Government & Regulatory Fees")
B97: 53500 | C97: Regulatory & Facilitation | F97: Cost of Sales | H97: =SUMIFS(Entries!$G$2:$G$155,Entries!$C$2:$C$155,"Cost of Sales:Project Development Cost:Regulatory & Facilitation")-SUMIFS(Entries!$H$2:$H$155,Entries!$C$2:$C$155,"Cost of Sales:Project Development Cost:Regulatory & Facilitation")
B98: 60100 | C98: Advertising & Promotion | F98: Marketing & Sales Expenses | H98: =SUMIFS(Entries!$G$2:$G$155,Entries!$C$2:$C$155,"Marketing & Sales Expenses:Advertising & Promotion")-SUMIFS(Entries!$H$2:$H$155,Entries!$C$2:$C$155,"Marketing & Sales Expenses:Advertising & Promotion")
B99: 60300 | C99: Marketing Printing & Material | F99: Marketing & Sales Expenses | H99: =SUMIFS(Entries!$G$2:$G$155,Entries!$C$2:$C$155,"Marketing & Sales Expenses:Marketing Printing & Material")-SUMIFS(Entries!$H$2:$H$155,Entries!$C$2:$C$155,"Marketing & Sales Expenses:Marketing Printing & Material")
B100: 60400 | C100: Events & Client Entertainment | F100: Marketing & Sales Expenses | H100: =SUMIFS(Entries!$G$2:$G$155,Entries!$C$2:$C$155,"Marketing & Sales Expenses:Events & Client Entertainment")-SUMIFS(Entries!$H$2:$H$155,Entries!$C$2:$C$155,"Marketing & Sales Expenses:Events & Client Entertainment")
B101: 70100 | C101: Salaries & Wages | F101: Administrative Expenses | H101: =SUMIFS(Entries!$G$2:$G$155,Entries!$C$2:$C$155,"Administrative Expenses:Salaries & Wages",Entries!$J$2:$J$155,"16-Sep")-SUMIFS(Entries!$H$2:$H$155,Entries!$C$2:$C$155,"Administrative Expenses:Salaries & Wages",Entries!$J$2:$J$155,"16-Sep")
B102: 70500 | C102: Printing & Stationery | F102: Administrative Expenses | H102: =SUMIFS(Entries!$G$2:$G$155,Entries!$C$2:$C$155,"Administrative Expenses:Printing & Stationery")-SUMIFS(Entries!$H$2:$H$155,Entries!$C$2:$C$155,"Administrative Expenses:Printing & Stationery")
B103: 81100 | C103: Donations, Sadqa & Khairat | F103: Other Operating Expenses | H103: =SUMIFS(Entries!$G$2:$G$155,Entries!$C$2:$C$155,"Other Operating Expenses:Donations, Sadqa & Khairat")-SUMIFS(Entries!$H$2:$H$155,Entries!$C$2:$C$155,"Other Operating Expenses:Donations, Sadqa & Khairat")
G104: Total | H104: =SUM(H90:H103)
B106: Checks
B107: 1 | C107: Total debit equals total credit (all entries) | G107: Must pass | H107: =IF(K107=0,"✓ OK",IF(G107="Review","! "&K107&" to review","✗ "&K107&" issue")) | K107: =IF(ROUND(SUM(Entries!$G$2:$G$155)-SUM(Entries!$H$2:$H$155),2)=0,0,1)
B108: 2 | C108: Every account exists in the Awami Market COA | G108: Must pass | H108: =IF(K108=0,"✓ OK",IF(G108="Review","! "&K108&" to review","✗ "&K108&" issue")) | K108: =SUMPRODUCT((Entries!$D$2:$D$155="")*1)
B109: 3 | C109: Token table ties to account 21100 | G109: Must pass | H109: =IF(K109=0,"✓ OK",IF(G109="Review","! "&K109&" to review","✗ "&K109&" issue")) | K109: =IF(ROUND(H37-(SUMIFS(Entries!$H$2:$H$155,Entries!$C$2:$C$155,"Customer Advances:Token Money - Units")-SUMIFS(Entries!$G$2:$G$155,Entries!$C$2:$C$155,"Customer Advances:Token Money - Units")),0)=0,0,1)
B110: 4 | C110: Payments + head summary tie | G110: Must pass | H110: =IF(K110=0,"✓ OK",IF(G110="Review","! "&K110&" to review","✗ "&K110&" issue")) | K110: =IF(ROUND(H75-H104,0)=0,0,1)
B111: 5 | C111: Cash in hand, petty and bank not negative | G111: Must pass | H111: =IF(K111=0,"✓ OK",IF(G111="Review","! "&K111&" to review","✗ "&K111&" issue")) | K111: =COUNTIF(H10:H12,"<0")
...

Sheet 17-Sep
B2: FOURTEEN GROUP · AWAMI MARKET, KARKHANO | G2: Date | H2: 46282
B3: Daily Closing | G3: Day | H3: =TEXT(H2,"dddd")
B6: Opening Balance | C6: Money In | D6: Money Out | E6: Closing Balance | F6: =IF(SUM(K54:K57)=0,"✓ Balanced","⚠ Needs Review")
B7: =D14 | C7: =E14 | D7: =F14 | E7: =H14
B9: Cash & Bank
C10: Account | D10: Opening Balance | E10: Money In | F10: Money Out | G10: Transfer/Adjust | H10: Closing Balance
C11: Cash in Hand | D11: ='16-Sep'!H10 | E11: =SUMIFS($H$19:$H$26,$G$19:$G$26,"Cash") | F11: =SUMIFS($H$32:$H$41,$G$32:$G$41,"Cash") | G11: =-$D$15+$F$15-$H$15 | H11: =D11+E11-F11+G11
C12: Petty Cash | D12: ='16-Sep'!H11 | E12: =SUMIFS($H$19:$H$26,$G$19:$G$26,"Petty") | F12: =SUMIFS($H$32:$H$41,$G$32:$G$41,"Petty") | G12: =$H$15 | H12: =D12+E12-F12+G12
C13: Bank Al-Habib | D13: ='16-Sep'!H12 | E13: =SUMIFS($H$19:$H$26,$G$19:$G$26,"Bank") | F13: =SUMIFS($H$32:$H$41,$G$32:$G$41,"Bank") | G13: =$D$15-$F$15 | H13: =D13+E13-F13+G13
C14: Total | D14: =SUM(D11:D13) | E14: =SUM(E11:E13) | F14: =SUM(F11:F13) | G14: =SUM(G11:G13) | H14: =SUM(H11:H13)
C15: Cash → Bank Deposit | E15: Bank → Cash Withdrawal | G15: Cash → Petty Cash
B17: Money Received
B18: Voucher | C18: Description | D18: Head | F18: Floor | G18: Cash/Bank | H18: Amount Received
K19: =IF(D19="","",IFERROR(VALUE(LEFT(D19,5)),""))
K20: =IF(D20="","",IFERROR(VALUE(LEFT(D20,5)),""))
K21: =IF(D21="","",IFERROR(VALUE(LEFT(D21,5)),""))
K22: =IF(D22="","",IFERROR(VALUE(LEFT(D22,5)),""))
K23: =IF(D23="","",IFERROR(VALUE(LEFT(D23,5)),""))
K24: =IF(D24="","",IFERROR(VALUE(LEFT(D24,5)),""))
K25: =IF(D25="","",IFERROR(VALUE(LEFT(D25,5)),""))
K26: =IF(D26="","",IFERROR(VALUE(LEFT(D26,5)),""))
C27: =COUNT($H$19:$H$26)&" entries" | G27: Total Received | H27: =SUM($H$19:$H$26)
B30: Money Paid
B31: Voucher | C31: Description | D31: Head | F31: Floor | G31: Cash/Bank | H31: Amount Paid
K32: =IF(D32="","",IFERROR(VALUE(LEFT(D32,5)),""))
K33: =IF(D33="","",IFERROR(VALUE(LEFT(D33,5)),""))
K34: =IF(D34="","",IFERROR(VALUE(LEFT(D34,5)),""))
K35: =IF(D35="","",IFERROR(VALUE(LEFT(D35,5)),""))
K36: =IF(D36="","",IFERROR(VALUE(LEFT(D36,5)),""))
K37: =IF(D37="","",IFERROR(VALUE(LEFT(D37,5)),""))
K38: =IF(D38="","",IFERROR(VALUE(LEFT(D38,5)),""))
K39: =IF(D39="","",IFERROR(VALUE(LEFT(D39,5)),""))
K40: =IF(D40="","",IFERROR(VALUE(LEFT(D40,5)),""))
K41: =IF(D41="","",IFERROR(VALUE(LEFT(D41,5)),""))
C42: =COUNT($H$32:$H$41)&" entries" | G42: Total Paid | H42: =SUM($H$32:$H$41)
B44: Other Balances (Not Awami's Own Cash)
B45: Owed to FMH (payable) | G45: ='16-Sep'!H15*-1
B46: Owed to KBH (payable) | G46: ='16-Sep'!H16*-1
B47: Due from Syed Yousaf Shah — given by Awami, to be recovered | G47: ='16-Sep'!H14
B48: Due from Naeem Hussain — given by Awami, to be recovered | G48: 0
B49: Customer token money held — refundable if a deal is cancelled | G49: ='16-Sep'!H17*-1
B52: Check
B53: =IF(SUM(K54:K57)=0,"✓ Everything Matches — Closing is Correct","⚠ Please Review: "&IF(K54>0,"Some entries are incomplete (description/head/floor/cash-bank missing) ","")&IF(K55>0,"A head was not chosen from the list ","")&IF(K56>0,"A voucher number is used twice ","")&IF(K57>0,"Cash or Bank balance has gone negative ",""))
K54: =SUMPRODUCT(($H$19:$H$26<>"")*((($B$19:$B$26="")+($D$19:$D$26="")+($F$19:$F$26="")+($G$19:$G$26=""))>0))+SUMPRODUCT(($H$32:$H$41<>"")*((($B$32:$B$41="")+($D$32:$D$41="")+($F$32:$F$41="")+($G$32:$G$41=""))>0))
K55: =SUMPRODUCT(($D$19:$D$26<>"")*(COUNTIF(Heads!$E$2:$E$150,$D$19:$D$26)=0))+SUMPRODUCT(($D$32:$D$41<>"")*(COUNTIF(Heads!$E$2:$E$150,$D$32:$D$41)=0))
K56: =SUMPRODUCT(($B$19:$B$26<>"")*(COUNTIF($B$19:$B$41,$B$19:$B$26)>1))+SUMPRODUCT(($B$32:$B$41<>"")*(COUNTIF($B$19:$B$41,$B$32:$B$41)>1))
K57: =COUNTIF($H$11:$H$13,"<0")
B62: Prepared by (Accountant) | D62: Checked by | G62: Reviewed by Director
B64: Blue = enter manually · Everything else calculates automatically · Tomorrow's opening balance comes from here

Sheet Entries
A1: Voucher | B1: Date | C1: Account | D1: COA code | E1: Name | F1: Class | G1: Debit | H1: Credit | I1: Memo | J1: Closing
A2: JV-0001 | B2: 46213 | C2: Due to / from Group Companies:FMH - Fourteen Manzil Heights | D2: 22100 | E2: FMH | F2: Project-wide | G2: 10000 | I2: Token 102 received by FMH office - Cash | J2: 16-Sep
A3: JV-0001 | B3: 46213 | C3: Customer Advances:Token Money - Units | D3: 21100 | E3: Suhail:GF-129 | F3: GF | H3: 10000 | I3: Token 102 - unit GF-129 | J3: 16-Sep
A4: JV-0002 | B4: 46232 | C4: Due to / from Group Companies:FMH - Fourteen Manzil Heights | D4: 22100 | E4: FMH | F4: Project-wide | G4: 40000 | I4: Token 103 received by FMH office - Online to 14 Development | J4: 16-Sep
A5: JV-0002 | B5: 46232 | C5: Customer Advances:Token Money - Units | D5: 21100 | E5: Hassan Jan:GF-129 | F5: GF | H5: 40000 | I5: Token 103 - unit GF-129 | J5: 16-Sep
A6: JV-0003 | B6: 46253 | C6: Due to / from Group Companies:FMH - Fourteen Manzil Heights | D6: 22100 | E6: FMH | F6: Project-wide | G6: 10000 | I6: Token 105 received by FMH office - Cash | J6: 16-Sep
A7: JV-0003 | B7: 46253 | C7: Customer Advances:Token Money - Units | D7: 21100 | E7: Raza Ullah:GF-112 | F7: GF | H7: 10000 | I7: Token 105 - unit GF-112 | J7: 16-Sep
A8: JV-0004 | B8: 46253 | C8: Due to / from Group Companies:FMH - Fourteen Manzil Heights | D8: 22100 | E8: FMH | F8: Project-wide | G8: 10000 | I8: Token 106 received by FMH office - Cash | J8: 16-Sep
A9: JV-0004 | B9: 46253 | C9: Customer Advances:Token Money - Units | D9: 21100 | E9: Raza Ullah:GF-176 | F9: GF | H9: 10000 | I9: Token 106 - unit GF-176 | J9: 16-Sep
A10: JV-0005 | B10: 46262 | C10: Due to / from Group Companies:FMH - Fourteen Manzil Heights | D10: 22100 | E10: FMH | F10: Project-wide | G10: 10000 | I10: Token 107 received by FMH office - Cash | J10: 16-Sep
A11: JV-0005 | B11: 46262 | C11: Customer Advances:Token Money - Units | D11: 21100 | E11: Samin Khan Bangash:LG-132 | F11: LG | H11: 5000 | I11: Token 107 - unit LG-132 | J11: 16-Sep
A12: JV-0005 | B12: 46262 | C12: Customer Advances:Token Money - Units | D12: 21100 | E12: Samin Khan Bangash:LG-133 | F12: LG | H12: 5000 | I12: Token 107 - unit LG-133 | J12: 16-Sep
A13: JV-0006 | B13: 46266 | C13: Due to / from Group Companies:FMH - Fourteen Manzil Heights | D13: 22100 | E13: FMH | F13: Project-wide | G13: 100000 | I13: Token 108 received by FMH office - Online to 14 Development | J13: 16-Sep
A14: JV-0006 | B14: 46266 | C14: Customer Advances:Token Money - Units | D14: 21100 | E14: Hassan Jan:GF-129 | F14: GF | H14: 100000 | I14: Token 108 - unit GF-129 | J14: 16-Sep
A15: JV-0007 | B15: 46269 | C15: Due to / from Group Companies:FMH - Fourteen Manzil Heights | D15: 22100 | E15: FMH | F15: Project-wide | G15: 500000 | I15: Token 109 received by FMH office - Cash | J15: 16-Sep
A16: JV-0007 | B16: 46269 | C16: Customer Advances:Token Money - Units | D16: 21100 | E16: Haji Ibrar:LG-05 | F16: LG | H16: 55555.56 | I16: Token 109 - unit LG-05 | J16: 16-Sep
A17: JV-0007 | B17: 46269 | C17: Customer Advances:Token Money - Units | D17: 21100 | E17: Haji Ibrar:LG-06 | F17: LG | H17: 55555.56 | I17: Token 109 - unit LG-06 | J17: 16-Sep
A18: JV-0007 | B18: 46269 | C18: Customer Advances:Token Money - Units | D18: 21100 | E18: Waqar Ahmad - Units:LG-47 | F18: LG | H18: 55555.56 | I18: Token 109 - unit LG-47 | J18: 16-Sep
A19: JV-0007 | B19: 46269 | C19: Customer Advances:Token Money - Units | D19: 21100 | E19: Waqar Ahmad - Units:LG-48 | F19: LG | H19: 55555.56 | I19: Token 109 - unit LG-48 | J19: 16-Sep
A20: JV-0007 | B20: 46269 | C20: Customer Advances:Token Money - Units | D20: 21100 | E20: Waqar Ahmad - Units:LG-49 | F20: LG | H20: 55555.56 | I20: Token 109 - unit LG-49 | J20: 16-Sep
A21: JV-0007 | B21: 46269 | C21: Customer Advances:Token Money - Units | D21: 21100 | E21: Waqar Ahmad - Units:LG-50 | F21: LG | H21: 55555.56 | I21: Token 109 - unit LG-50 | J21: 16-Sep
A22: JV-0007 | B22: 46269 | C22: Customer Advances:Token Money - Units | D22: 21100 | E22: Waqar Ahmad - Units:LG-91 | F22: LG | H22: 55555.56 | I22: Token 109 - unit LG-91 | J22: 16-Sep
A23: JV-0007 | B23: 46269 | C23: Customer Advances:Token Money - Units | D23: 21100 | E23: Waqar Ahmad - Units:LG-92 | F23: LG | H23: 55555.56 | I23: Token 109 - unit LG-92 | J23: 16-Sep
A24: JV-0007 | B24: 46269 | C24: Customer Advances:Token Money - Units | D24: 21100 | E24: Waqar Ahmad - Units:LG-93 | F24: LG | H24: 55555.52 | I24: Token 109 - unit LG-93 | J24: 16-Sep
A25: JV-0008 | B25: 46269 | C25: Due to / from Group Companies:FMH - Fourteen Manzil Heights | D25: 22100 | E25: FMH | F25: Project-wide | G25: 200000 | I25: Token 110 received by FMH office - Cash | J25: 16-Sep
A26: JV-0008 | B26: 46269 | C26: Customer Advances:Token Money - Units | D26: 21100 | E26: Hussain:LG-54 | F26: LG | H26: 100000 | I26: Token 110 - unit LG-54 | J26: 16-Sep
A27: JV-0008 | B27: 46269 | C27: Customer Advances:Token Money - Units | D27: 21100 | E27: Hussain:LG-97 | F27: LG | H27: 100000 | I27: Token 110 - unit LG-97 | J27: 16-Sep
A28: JV-0009 | B28: 46270 | C28: Due to / from Group Companies:FMH - Fourteen Manzil Heights | D28: 22100 | E28: FMH | F28: Project-wide | G28: 600000 | I28: Token 111 received by FMH office - Cash | J28: 16-Sep
A29: JV-0009 | B29: 46270 | C29: Customer Advances:Token Money - Units | D29: 21100 | E29: Haji Ibrar:LG-01 | F29: LG | H29: 66666.67 | I29: Token 111 - unit LG-01 | J29: 16-Sep
A30: JV-0009 | B30: 46270 | C30: Customer Advances:Token Money - Units | D30: 21100 | E30: Haji Ibrar:LG-02 | F30: LG | H30: 66666.67 | I30: Token 111 - unit LG-02 | J30: 16-Sep
A31: JV-0009 | B31: 46270 | C31: Customer Advances:Token Money - Units | D31: 21100 | E31: Haji Ibrar:LG-03 | F31: LG | H31: 66666.67 | I31: Token 111 - unit LG-03 | J31: 16-Sep
A32: JV-0009 | B32: 46270 | C32: Customer Advances:Token Money - Units | D32: 21100 | E32: Haji Ibrar:LG-04 | F32: LG | H32: 66666.67 | I32: Token 111 - unit LG-04 | J32: 16-Sep
A33: JV-0009 | B33: 46270 | C33: Customer Advances:Token Money - Units | D33: 21100 | E33: Haji Ibrar:LG-05 | F33: LG | H33: 66666.67 | I33: Token 111 - unit LG-05 | J33: 16-Sep
A34: JV-0009 | B34: 46270 | C34: Customer Advances:Token Money - Units | D34: 21100 | E34: Haji Ibrar:LG-06 | F34: LG | H34: 66666.67 | I34: Token 111 - unit LG-06 | J34: 16-Sep
A35: JV-0009 | B35: 46270 | C35: Customer Advances:Token Money - Units | D35: 21100 | E35: Haji Ibrar:LG-07 | F35: LG | H35: 66666.67 | I35: Token 111 - unit LG-07 | J35: 16-Sep
A36: JV-0009 | B36: 46270 | C36: Customer Advances:Token Money - Units | D36: 21100 | E36: Haji Ibrar:LG-08 | F36: LG | H36: 66666.67 | I36: Token 111 - unit LG-08 | J36: 16-Sep
A37: JV-0009 | B37: 46270 | C37: Customer Advances:Token Money - Units | D37: 21100 | E37: Haji Ibrar:LG-09 | F37: LG | H37: 66666.64 | I37: Token 111 - unit LG-09 | J37: 16-Sep
A38: JV-0010 | B38: 46270 | C38: Due to / from Group Companies:FMH - Fourteen Manzil Heights | D38: 22100 | E38: FMH | F38: Project-wide | G38: 500000 | I38: Token 112 received by FMH office - Cash | J38: 16-Sep
A39: JV-0010 | B39: 46270 | C39: Customer Advances:Token Money - Units | D39: 21100 | E39: Malak Ibrar:GF-13 | F39: GF | H39: 500000 | I39: Token 112 - unit GF-13 | J39: 16-Sep
A40: JV-0011 | B40: 46276 | C40: Current Assets:Due from Directors:Syed Yousaf Shah | D40: 12610 | E40: Syed Yousaf Shah | F40: Project-wide | G40: 800000 | I40: Token 113 received by Syed Yousaf Shah - Cash | J40: 16-Sep
A41: JV-0011 | B41: 46276 | C41: Customer Advances:Token Money - Units | D41: 21100 | E41: Meena Gul:LG-51 | F41: LG | H41: 114285.71 | I41: Token 113 - unit LG-51 | J41: 16-Sep
A42: JV-0011 | B42: 46276 | C42: Customer Advances:Token Money - Units | D42: 21100 | E42: Meena Gul:LG-52 | F42: LG | H42: 114285.71 | I42: Token 113 - unit LG-52 | J42: 16-Sep
A43: JV-0011 | B43: 46276 | C43: Customer Advances:Token Money - Units | D43: 21100 | E43: Meena Gul:LG-53 | F43: LG | H43: 114285.71 | I43: Token 113 - unit LG-53 | J43: 16-Sep
A44: JV-0011 | B44: 46276 | C44: Customer Advances:Token Money - Units | D44: 21100 | E44: Meena Gul:LG-94 | F44: LG | H44: 114285.71 | I44: Token 113 - unit LG-94 | J44: 16-Sep
A45: JV-0011 | B45: 46276 | C45: Customer Advances:Token Money - Units | D45: 21100 | E45: Meena Gul:LG-95 | F45: LG | H45: 114285.71 | I45: Token 113 - unit LG-95 | J45: 16-Sep
A46: JV-0011 | B46: 46276 | C46: Customer Advances:Token Money - Units | D46: 21100 | E46: Meena Gul:LG-96 | F46: LG | H46: 114285.71 | I46: Token 113 - unit LG-96 | J46: 16-Sep
A47: JV-0011 | B47: 46276 | C47: Customer Advances:Token Money - Units | D47: 21100 | E47: Meena Gul:GF-90 | F47: GF | H47: 114285.74 | I47: Token 113 - unit GF-90 | J47: 16-Sep
A48: JV-0012 | B48: 46279 | C48: Due to / from Group Companies:FMH - Fourteen Manzil Heights | D48: 22100 | E48: FMH | F48: Project-wide | G48: 100000 | I48: Token 114 received by FMH office - Cash | J48: 16-Sep
A49: JV-0012 | B49: 46279 | C49: Customer Advances:Token Money - Units | D49: 21100 | E49: Azhar Ud Din:LG-10 | F49: LG | H49: 100000 | I49: Token 114 - unit LG-10 | J49: 16-Sep
A50: JV-0013 | B50: 46279 | C50: Due to / from Group Companies:FMH - Fourteen Manzil Heights | D50: 22100 | E50: FMH | F50: Project-wide | G50: 200000 | I50: Token 115 received by FMH office - Cash | J50: 16-Sep
A51: JV-0013 | B51: 46279 | C51: Customer Advances:Token Money - Units | D51: 21100 | E51: Sudais:LG-55 | F51: LG | H51: 100000 | I51: Token 115 - unit LG-55 | J51: 16-Sep
A52: JV-0013 | B52: 46279 | C52: Customer Advances:Token Money - Units | D52: 21100 | E52: Shuraim:LG-98 | F52: LG | H52: 100000 | I52: Token 115 - unit LG-98 | J52: 16-Sep
A53: JV-0014 | B53: 46279 | C53: Due to / from Group Companies:FMH - Fourteen Manzil Heights | D53: 22100 | E53: FMH | F53: Project-wide | G53: 200000 | I53: Token 116 received by FMH office - Cash | J53: 16-Sep
A54: JV-0014 | B54: 46279 | C54: Customer Advances:Token Money - Units | D54: 21100 | E54: Salman:CB-16 | F54: CB | H54: 100000 | I54: Token 116 - unit CB-16 | J54: 16-Sep
A55: JV-0014 | B55: 46279 | C55: Customer Advances:Token Money - Units | D55: 21100 | E55: Salman:CB-45 | F55: CB | H55: 100000 | I55: Token 116 - unit CB-45 | J55: 16-Sep
A56: JV-0015 | B56: 46276 | C56: Current Assets:Due from Directors:Syed Yousaf Shah | D56: 12610 | E56: Syed Yousaf Shah | F56: Project-wide | G56: 2300000 | I56: Token money handed over by FMH office | J56: 16-Sep
A57: JV-0015 | B57: 46276 | C57: Due to / from Group Companies:FMH - Fourteen Manzil Heights | D57: 22100 | E57: FMH | F57: Project-wide | H57: 2300000 | I57: Token money handed over to Syed Yousaf Shah | J57: 16-Sep
A58: JV-0016 | B58: 46189 | C58: Due to / from Group Companies:FMH - Fourteen Manzil Heights | D58: 22100 | E58: FMH | F58: Project-wide | G58: 250000 | I58: Token 101 - unit LG-03 - Abdullah | J58: 16-Sep
A59: JV-0016 | B59: 46189 | C59: Customer Advances:Token Money - Units | D59: 21100 | E59: Abdullah:LG-03 | F59: LG | H59: 250000 | I59: Token 101 - unit LG-03 - Abdullah | J59: 16-Sep
A60: JV-0017 | B60: 46283 | C60: Customer Advances:Token Money - Units | D60: 21100 | E60: Abdullah:LG-03 | F60: LG | G60: 250000 | I60: Token 101 returned to Abdullah - unit LG-03 | J60: 16-Sep
A61: JV-0017 | B61: 46283 | C61: Due to / from Group Companies:FMH - Fourteen Manzil Heights | D61: 22100 | E61: FMH | F61: Project-wide | H61: 250000 | I61: Token 101 returned to Abdullah - unit LG-03 | J61: 16-Sep
A62: JV-0018 | B62: 46059 | C62: Cost of Sales:Land Cost:Land Purchase Cost | D62: 51100 | E62: Syed Yousaf Shah | F62: Project-wide | G62: 10000000 | I62: Ch# 10318764 deposited to Yousaf saib UBL | J62: 16-Sep
A63: JV-0018 | B63: 46059 | C63: Due to / from Group Companies:FMH - Fourteen Manzil Heights | D63: 22100 | E63: FMH | F63: Project-wide | H63: 10000000 | I63: Paid by FMH for Awami Market - Ch# 10318764 deposited to Yousaf saib UBL | J63: 16-Sep
A64: JV-0019 | B64: 46111 | C64: Cost of Sales:Land Cost:Land Purchase Cost | D64: 51100 | E64: Syed Yousaf Shah | F64: Project-wide | G64: 4000000 | I64: Ch# 10323992 issued to Yousaf saib as loan return | J64: 16-Sep
A65: JV-0019 | B65: 46111 | C65: Due to / from Group Companies:FMH - Fourteen Manzil Heights | D65: 22100 | E65: FMH | F65: Project-wide | H65: 4000000 | I65: Paid by FMH for Awami Market - Ch# 10323992 issued to Yousaf saib as loan return | J65: 16-Sep
A66: JV-0020 | B66: 46111 | C66: Cost of Sales:Land Cost:Land Purchase Cost | D66: 51100 | E66: Syed Yousaf Shah | F66: Project-wide | G66: 4000000 | I66: Ch# 10323992 issued to Yousaf saib as loan return - second entry | J66: 16-Sep
A67: JV-0020 | B67: 46111 | C67: Due to / from Group Companies:FMH - Fourteen Manzil Heights | D67: 22100 | E67: FMH | F67: Project-wide | H67: 4000000 | I67: Paid by FMH for Awami Market - Ch# 10323992 issued to Yousaf saib as loan return - second entry | J67: 16-Sep
A68: JV-0021 | B68: 46129 | C68: Administrative Expenses:Printing & Stationery | D68: 70500 | E68: Kashif | F68: Project-wide | G68: 15000 | I68: Paid to Kashif as stamp navi | J68: 16-Sep
A69: JV-0021 | B69: 46129 | C69: Due to / from Group Companies:FMH - Fourteen Manzil Heights | D69: 22100 | E69: FMH | F69: Project-wide | H69: 15000 | I69: Paid by FMH for Awami Market - Paid to Kashif as stamp navi | J69: 16-Sep
A70: JV-0022 | B70: 46132 | C70: Marketing & Sales Expenses:Marketing Printing & Material | D70: 60300 | E70: Waqar Easypaisa | F70: Project-wide | G70: 10000 | I70: Paid to Waqar easypaisa for project MAP | J70: 16-Sep
A71: JV-0022 | B71: 46132 | C71: Due to / from Group Companies:FMH - Fourteen Manzil Heights | D71: 22100 | E71: FMH | F71: Project-wide | H71: 10000 | I71: Paid by FMH for Awami Market - Paid to Waqar easypaisa for project MAP | J71: 16-Sep
A72: JV-0023 | B72: 46133 | C72: Cost of Sales:Project Development Cost:Architecture, Design & Drawings | D72: 53100 | E72: Shah Khalid | F72: Project-wide | G72: 500000 | I72: Paid to Shah Khalid online by Naeem saib | J72: 16-Sep
A73: JV-0023 | B73: 46133 | C73: Due to / from Group Companies:FMH - Fourteen Manzil Heights | D73: 22100 | E73: FMH | F73: Project-wide | H73: 500000 | I73: Paid by FMH for Awami Market - Paid to Shah Khalid online by Naeem saib | J73: 16-Sep
A74: JV-0024 | B74: 46135 | C74: Cost of Sales:Project Development Cost:Soil Testing & Survey | D74: 53200 | E74: Alam | F74: Project-wide | G74: 100000 | I74: Ch# 10324016 issued to Alam c/o Dr Irshad | J74: 16-Sep
A75: JV-0024 | B75: 46135 | C75: Due to / from Group Companies:FMH - Fourteen Manzil Heights | D75: 22100 | E75: FMH | F75: Project-wide | H75: 100000 | I75: Paid by FMH for Awami Market - Ch# 10324016 issued to Alam c/o Dr Irshad | J75: 16-Sep
A76: JV-0025 | B76: 46136 | C76: Fixed Assets:Computer & IT Equipment | D76: 15300 | E76: Rashid | F76: Project-wide | G76: 95000 | I76: Paid for laptop c/o Rashid | J76: 15-Sep
A77: JV-0025 | B77: 46136 | C77: Due to / from Group Companies:FMH - Fourteen Manzil Heights | D77: 22100 | E77: FMH | F77: Project-wide | H77: 95000 | I77: Paid by FMH for Awami Market - Paid for laptop c/o Rashid | J77: 15-Sep
A78: JV-0026 | B78: 46139 | C78: Fixed Assets:Computer & IT Equipment | D78: 15300 | F78: Project-wide | G78: 35000 | I78: Paid for Kharkhano map laptop | J78: 16-Sep
A79: JV-0026 | B79: 46139 | C79: Due to / from Group Companies:FMH - Fourteen Manzil Heights | D79: 22100 | E79: FMH | F79: Project-wide | H79: 35000 | I79: Paid by FMH for Awami Market - Paid for Kharkhano map laptop | J79: 16-Sep
A80: JV-0027 | B80: 46142 | C80: Cost of Sales:Project Development Cost:Regulatory & Facilitation | D80: 53500 | E80: Noor Zaman TMA | F80: Project-wide | G80: 100000 | I80: Paid to Noor Zaman TMA b/o Yousaf saib | J80: 16-Sep
A81: JV-0027 | B81: 46142 | C81: Due to / from Group Companies:FMH - Fourteen Manzil Heights | D81: 22100 | E81: FMH | F81: Project-wide | H81: 100000 | I81: Paid by FMH for Awami Market - Paid to Noor Zaman TMA b/o Yousaf saib | J81: 16-Sep
A82: JV-0028 | B82: 46146 | C82: Cost of Sales:Project Development Cost:Soil Testing & Survey | D82: 53200 | E82: Alam | F82: Project-wide | G82: 100000 | I82: Paid to Alam c/o Dr Irshad | J82: 16-Sep
A83: JV-0028 | B83: 46146 | C83: Due to / from Group Companies:FMH - Fourteen Manzil Heights | D83: 22100 | E83: FMH | F83: Project-wide | H83: 100000 | I83: Paid by FMH for Awami Market - Paid to Alam c/o Dr Irshad | J83: 16-Sep
A84: JV-0029 | B84: 46147 | C84: Administrative Expenses:Salaries & Wages | D84: 70100 | E84: Rashid | F84: Project-wide | G84: 50000 | I84: Paid to Rashid as salary April 2026 | J84: 15-Sep
A85: JV-0029 | B85: 46147 | C85: Due to / from Group Companies:FMH - Fourteen Manzil Heights | D85: 22100 | E85: FMH | F85: Project-wide | H85: 50000 | I85: Paid by FMH for Awami Market - Paid to Rashid as salary April 2026 | J85: 15-Sep
A86: JV-0030 | B86: 46178 | C86: Other Assets:Software & Licences | D86: 16100 | E86: Rashid | F86: Project-wide | G86: 100000 | I86: Paid to Rashid for QuickBooks | J86: 15-Sep
A87: JV-0030 | B87: 46178 | C87: Due to / from Group Companies:FMH - Fourteen Manzil Heights | D87: 22100 | E87: FMH | F87: Project-wide | H87: 100000 | I87: Paid by FMH for Awami Market - Paid to Rashid for QuickBooks | J87: 15-Sep
A88: JV-0031 | B88: 46163 | C88: Administrative Expenses:Printing & Stationery | D88: 70500 | E88: RX Printings | F88: Project-wide | G88: 20000 | I88: Paid to RX Printings, receipts etc | J88: 16-Sep
A89: JV-0031 | B89: 46163 | C89: Due to / from Group Companies:FMH - Fourteen Manzil Heights | D89: 22100 | E89: FMH | F89: Project-wide | H89: 20000 | I89: Paid by FMH for Awami Market - Paid to RX Printings, receipts etc | J89: 16-Sep
A90: JV-0032 | B90: 46175 | C90: Other Assets:Software & Licences | D90: 16100 | E90: Rashid | F90: Project-wide | G90: 80000 | I90: Paid to Rashid saib for QuickBooks software | J90: 15-Sep
A91: JV-0032 | B91: 46175 | C91: Due to / from Group Companies:FMH - Fourteen Manzil Heights | D91: 22100 | E91: FMH | F91: Project-wide | H91: 80000 | I91: Paid by FMH for Awami Market - Paid to Rashid saib for QuickBooks software | J91: 15-Sep
A92: JV-0033 | B92: 46178 | C92: Administrative Expenses:Printing & Stationery | D92: 70500 | F92: Project-wide | G92: 45000 | I92: Paid for receipt books CRV CPV and tokens, Awami mobile | J92: 16-Sep
A93: JV-0033 | B93: 46178 | C93: Due to / from Group Companies:FMH - Fourteen Manzil Heights | D93: 22100 | E93: FMH | F93: Project-wide | H93: 45000 | I93: Paid by FMH for Awami Market - Paid for receipt books CRV CPV and tokens, Awami mobile | J93: 16-Sep
A94: JV-0034 | B94: 46181 | C94: Cost of Sales:Project Development Cost:Government & Regulatory Fees | D94: 53400 | E94: PRF | F94: Project-wide | G94: 850000 | I94: Ch# 10324046 issued to PRF | J94: 16-Sep
A95: JV-0034 | B95: 46181 | C95: Due to / from Group Companies:FMH - Fourteen Manzil Heights | D95: 22100 | E95: FMH | F95: Project-wide | H95: 850000 | I95: Paid by FMH for Awami Market - Ch# 10324046 issued to PRF | J95: 16-Sep
A96: JV-0035 | B96: 46182 | C96: Cost of Sales:Project Development Cost:Soil Testing & Survey | D96: 53200 | E96: Eng Hamza | F96: Project-wide | G96: 100000 | I96: Ch# 10324047 issued for soil testing by Eng Hamza | J96: 16-Sep
A97: JV-0035 | B97: 46182 | C97: Due to / from Group Companies:FMH - Fourteen Manzil Heights | D97: 22100 | E97: FMH | F97: Project-wide | H97: 100000 | I97: Paid by FMH for Awami Market - Ch# 10324047 issued for soil testing by Eng Hamza | J97: 16-Sep
A98: JV-0036 | B98: 46182 | C98: Cost of Sales:Project Development Cost:Government & Regulatory Fees | D98: 53400 | E98: KPRA | F98: Project-wide | G98: 350000 | I98: Ch# 10324048 issued for KPRA payment by Yousaf saib | J98: 16-Sep
A99: JV-0036 | B99: 46182 | C99: Due to / from Group Companies:FMH - Fourteen Manzil Heights | D99: 22100 | E99: FMH | F99: Project-wide | H99: 350000 | I99: Paid by FMH for Awami Market - Ch# 10324048 issued for KPRA payment by Yousaf saib | J99: 16-Sep
A100: JV-0037 | B100: 46184 | C100: Cost of Sales:Project Development Cost:Regulatory & Facilitation | D100: 53500 | E100: PDA | F100: Project-wide | G100: 375000 | I100: Ch# 10324043 issued to PDA | J100: 16-Sep
...

Sheet Heads
A1: Code | B1: Head name | C1: QB type | D1: Parent | E1: Pick label | F1: Received | G1: Paid | H1: Used #
A2: 12100 | B2: Supplier & Contractor Advances | C2: Other Current Asset | D2: Current Assets | E2: =IF(A2="","",A2&" · "&B2) | F2: =IF(A2="","",SUMIFS('17-Sep'!$H$19:$H$26,'17-Sep'!$K$19:$K$26,A2)) | G2: =IF(A2="","",SUMIFS('17-Sep'!$H$32:$H$41,'17-Sep'!$K$32:$K$41,A2))
A3: 12200 | B3: Staff Advances | C3: Other Current Asset | D3: Current Assets | E3: =IF(A3="","",A3&" · "&B3) | F3: =IF(A3="","",SUMIFS('17-Sep'!$H$19:$H$26,'17-Sep'!$K$19:$K$26,A3)) | G3: =IF(A3="","",SUMIFS('17-Sep'!$H$32:$H$41,'17-Sep'!$K$32:$K$41,A3))
A4: 12300 | B4: PDC Receivable | C4: Other Current Asset | D4: Current Assets | E4: =IF(A4="","",A4&" · "&B4) | F4: =IF(A4="","",SUMIFS('17-Sep'!$H$19:$H$26,'17-Sep'!$K$19:$K$26,A4)) | G4: =IF(A4="","",SUMIFS('17-Sep'!$H$32:$H$41,'17-Sep'!$K$32:$K$41,A4))
A5: 12400 | B5: Prepaid Expenses | C5: Other Current Asset | D5: Current Assets | E5: =IF(A5="","",A5&" · "&B5) | F5: =IF(A5="","",SUMIFS('17-Sep'!$H$19:$H$26,'17-Sep'!$K$19:$K$26,A5)) | G5: =IF(A5="","",SUMIFS('17-Sep'!$H$32:$H$41,'17-Sep'!$K$32:$K$41,A5))
A6: 12500 | B6: Security Deposits | C6: Other Current Asset | D6: Current Assets | E6: =IF(A6="","",A6&" · "&B6) | F6: =IF(A6="","",SUMIFS('17-Sep'!$H$19:$H$26,'17-Sep'!$K$19:$K$26,A6)) | G6: =IF(A6="","",SUMIFS('17-Sep'!$H$32:$H$41,'17-Sep'!$K$32:$K$41,A6))
A7: 12610 | B7: Syed Yousaf Shah | C7: Other Current Asset | D7: Due from Directors | E7: =IF(A7="","",A7&" · "&B7) | F7: =IF(A7="","",SUMIFS('17-Sep'!$H$19:$H$26,'17-Sep'!$K$19:$K$26,A7)) | G7: =IF(A7="","",SUMIFS('17-Sep'!$H$32:$H$41,'17-Sep'!$K$32:$K$41,A7))
A8: 12620 | B8: Naeem Hussain | C8: Other Current Asset | D8: Due from Directors | E8: =IF(A8="","",A8&" · "&B8) | F8: =IF(A8="","",SUMIFS('17-Sep'!$H$19:$H$26,'17-Sep'!$K$19:$K$26,A8)) | G8: =IF(A8="","",SUMIFS('17-Sep'!$H$32:$H$41,'17-Sep'!$K$32:$K$41,A8))
A9: 13100 | B9: Unsold Units - Shops | C9: Other Current Asset | D9: Project Inventory | E9: =IF(A9="","",A9&" · "&B9) | F9: =IF(A9="","",SUMIFS('17-Sep'!$H$19:$H$26,'17-Sep'!$K$19:$K$26,A9)) | G9: =IF(A9="","",SUMIFS('17-Sep'!$H$32:$H$41,'17-Sep'!$K$32:$K$41,A9))
A10: 15100 | B10: Furniture & Fixtures | C10: Fixed Asset | D10: Fixed Assets | E10: =IF(A10="","",A10&" · "&B10) | F10: =IF(A10="","",SUMIFS('17-Sep'!$H$19:$H$26,'17-Sep'!$K$19:$K$26,A10)) | G10: =IF(A10="","",SUMIFS('17-Sep'!$H$32:$H$41,'17-Sep'!$K$32:$K$41,A10))
A11: 15200 | B11: Office Equipment | C11: Fixed Asset | D11: Fixed Assets | E11: =IF(A11="","",A11&" · "&B11) | F11: =IF(A11="","",SUMIFS('17-Sep'!$H$19:$H$26,'17-Sep'!$K$19:$K$26,A11)) | G11: =IF(A11="","",SUMIFS('17-Sep'!$H$32:$H$41,'17-Sep'!$K$32:$K$41,A11))
A12: 15300 | B12: Computer & IT Equipment | C12: Fixed Asset | D12: Fixed Assets | E12: =IF(A12="","",A12&" · "&B12) | F12: =IF(A12="","",SUMIFS('17-Sep'!$H$19:$H$26,'17-Sep'!$K$19:$K$26,A12)) | G12: =IF(A12="","",SUMIFS('17-Sep'!$H$32:$H$41,'17-Sep'!$K$32:$K$41,A12))
A13: 15400 | B13: Vehicles | C13: Fixed Asset | D13: Fixed Assets | E13: =IF(A13="","",A13&" · "&B13) | F13: =IF(A13="","",SUMIFS('17-Sep'!$H$19:$H$26,'17-Sep'!$K$19:$K$26,A13)) | G13: =IF(A13="","",SUMIFS('17-Sep'!$H$32:$H$41,'17-Sep'!$K$32:$K$41,A13))
... A78: 85200 | B78: Markup & Interest | C78: Expense | D78: Financial Charges | E78: =IF(A78="","",A78&" · "&B78) | F78: =IF(A78="","",SUMIFS('17-Sep'!$H$19:$H$26,'17-Sep'!$K$19:$K$26,A78)) | G78: =IF(A78="","",SUMIFS('17-Sep'!$H$32:$H$41,'17-Sep'!$K$32:$K$41,A78))
E79: =IF(A79="","",A79&" · "&B79) | F79: =IF(A79="","",SUMIFS('17-Sep'!$H$19:$H$26,'17-Sep'!$K$19:$K$26,A79)) | G79: =IF(A79="","",SUMIFS('17-Sep'!$H$32:$H$41,'17-Sep'!$K$32:$K$41,A79))
E80: =IF(A80="","",A80&" · "&B80) | F80: =IF(A80="","",SUMIFS('17-Sep'!$H$19:$H$26,'17-Sep'!$K$19:$K$26,A80)) | G80: =IF(A80="","",SUMIFS('17-Sep'!$H$32:$H$41,'17-Sep'!$K$32:$K$41,A80))
E81: =IF(A81="","",A81&" · "&B81) | F81: =IF(A81="","",SUMIFS('17-Sep'!$H$19:$H$26,'17-Sep'!$K$19:$K$26,A81)) | G81: =IF(A81="","",SUMIFS('17-Sep'!$H$32:$H$41,'17-Sep'!$K$32:$K$41,A81))
E82: =IF(A82="","",A82&" · "&B82) | F82: =IF(A82="","",SUMIFS('17-Sep'!$H$19:$H$26,'17-Sep'!$K$19:$K$26,A82)) | G82: =IF(A82="","",SUMIFS('17-Sep'!$H$32:$H$41,'17-Sep'!$K$32:$K$41,A82))
E83: =IF(A83="","",A83&" · "&B83) | F83: =IF(A83="","",SUMIFS('17-Sep'!$H$19:$H$26,'17-Sep'!$K$19:$K$26,A83)) | G83: =IF(A83="","",SUMIFS('17-Sep'!$H$32:$H$41,'17-Sep'!$K$32:$K$41,A83))
E84: =IF(A84="","",A84&" · "&B84) | F84: =IF(A84="","",SUMIFS('17-Sep'!$H$19:$H$26,'17-Sep'!$K$19:$K$26,A84)) | G84: =IF(A84="","",SUMIFS('17-Sep'!$H$32:$H$41,'17-Sep'!$K$32:$K$41,A84))
E85: =IF(A85="","",A85&" · "&B85) | F85: =IF(A85="","",SUMIFS('17-Sep'!$H$19:$H$26,'17-Sep'!$K$19:$K$26,A85)) | G85: =IF(A85="","",SUMIFS('17-Sep'!$H$32:$H$41,'17-Sep'!$K$32:$K$41,A85))
E86: =IF(A86="","",A86&" · "&B86) | F86: =IF(A86="","",SUMIFS('17-Sep'!$H$19:$H$26,'17-Sep'!$K$19:$K$26,A86)) | G86: =IF(A86="","",SUMIFS('17-Sep'!$H$32:$H$41,'17-Sep'!$K$32:$K$41,A86))
E87: =IF(A87="","",A87&" · "&B87) | F87: =IF(A87="","",SUMIFS('17-Sep'!$H$19:$H$26,'17-Sep'!$K$19:$K$26,A87)) | G87: =IF(A87="","",SUMIFS('17-Sep'!$H$32:$H$41,'17-Sep'!$K$32:$K$41,A87))
E88: =IF(A88="","",A88&" · "&B88) | F88: =IF(A88="","",SUMIFS('17-Sep'!$H$19:$H$26,'17-Sep'!$K$19:$K$26,A88)) | G88: =IF(A88="","",SUMIFS('17-Sep'!$H$32:$H$41,'17-Sep'!$K$32:$K$41,A88))
E89: =IF(A89="","",A89&" · "&B89) | F89: =IF(A89="","",SUMIFS('17-Sep'!$H$19:$H$26,'17-Sep'!$K$19:$K$26,A89)) | G89: =IF(A89="","",SUMIFS('17-Sep'!$H$32:$H$41,'17-Sep'!$K$32:$K$41,A89))
E90: =IF(A90="","",A90&" · "&B90) | F90: =IF(A90="","",SUMIFS('17-Sep'!$H$19:$H$26,'17-Sep'!$K$19:$K$26,A90)) | G90: =IF(A90="","",SUMIFS('17-Sep'!$H$32:$H$41,'17-Sep'!$K$32:$K$41,A90))
... E150: =IF(A150="","",A150&" · "&B150) | F150: =IF(A150="","",SUMIFS('17-Sep'!$H$19:$H$26,'17-Sep'!$K$19:$K$26,A150)) | G150: =IF(A150="","",SUMIFS('17-Sep'!$H$32:$H$41,'17-Sep'!$K$32:$K$41,A150))

Sheet Lists
A1: Class | B1: Via
A2: LG | B2: Cash
A3: GF | B3: Petty
A4: FF | B4: Bank
A5: SF
A6: TF
A7: 4F
A8: 5F
A9: CB
A10: Project-wide
